tests/__init__.py
tests/test_that_it_works.py
visualbench/__init__.py
visualbench/benchmark.py
visualbench/logger.py
visualbench/losses.py
visualbench/rng.py
visualbench/data/3x3 font.jpeg
visualbench/data/__init__.py
visualbench/data/attngrad-96.png
visualbench/data/biang-96.png
visualbench/data/emojis-96.png
visualbench/data/frog-96.png
visualbench/data/geometry-96.png
visualbench/data/grid-96.png
visualbench/data/maze-96.png
visualbench/data/qr-96.jpg
visualbench/data/rubic-96.png
visualbench/data/sanic-96.jpg
visualbench/data/sources.txt
visualbench/data/spiral-96.png
visualbench/data/test-96.jpg
visualbench/data/text-96.png
visualbench/data/weevil-96.png
visualbench/models/__init__.py
visualbench/models/act.py
visualbench/models/basic.py
visualbench/models/linear.py
visualbench/models/ode.py
visualbench/models/ssm.py
visualbench/models/torchvision.py
visualbench/models/vision.py
visualbench/models/wrappers.py
visualbench/runs/__init__.py
visualbench/runs/benchmark_benchmark.py
visualbench/runs/benchpack.py
visualbench/runs/colab_utils.py
visualbench/runs/fast_mlbench.py
visualbench/runs/mbs.py
visualbench/runs/mlbench.py
visualbench/runs/onedim_vis.py
visualbench/runs/optimizer_benchmark.py
visualbench/runs/plotting.py
visualbench/runs/run.py
visualbench/runs/tinybench.py
visualbench/runs/utils.py
visualbench/runs/visualbench.py
visualbench/tasks/__init__.py
visualbench/tasks/char_rnn.py
visualbench/tasks/colorization.py
visualbench/tasks/cutest.py
visualbench/tasks/data_fit.py
visualbench/tasks/function_approximator.py
visualbench/tasks/glimmer.py
visualbench/tasks/gmm.py
visualbench/tasks/graph_layout.py
visualbench/tasks/guassian_processes.py
visualbench/tasks/lennard_jones_clusters.py
visualbench/tasks/matrix_factorization.py
visualbench/tasks/minpack2.py
visualbench/tasks/muon_coeffs.py
visualbench/tasks/operations.py
visualbench/tasks/optimal_control.py
visualbench/tasks/pde.py
visualbench/tasks/racing.py
visualbench/tasks/registration.py
visualbench-1.0.6.dist-info/METADATA
visualbench-1.0.6.dist-info/WHEEL
visualbench-1.0.6.dist-info/top_level.txt
visualbench-1.0.6.dist-info/RECORD
