Metadata-Version: 2.4
Name: visualbench
Version: 1.0.6
Requires-Python: >=3.11
Requires-Dist: torch
Requires-Dist: numpy
Requires-Dist: scipy
Requires-Dist: more_itertools
Requires-Dist: matplotlib
Requires-Dist: opencv-python
